{
    "shapes": [
        {
            "label": "stroke",
            "points": [
                [
                    216,
                    300
                ],
                [
                    216,
                    301
                ],
                [
                    214,
                    303
                ],
                [
                    214,
                    311
                ],
                [
                    216,
                    313
                ],
                [
                    216,
                    314
                ],
                [
                    215,
                    315
                ],
                [
                    215,
                    316
                ],
                [
                    216,
                    316
                ],
                [
                    217,
                    317
                ],
                [
                    221,
                    317
                ],
                [
                    222,
                    318
                ],
                [
                    231,
                    318
                ],
                [
                    232,
                    317
                ],
                [
                    234,
                    317
                ],
                [
                    238,
                    313
                ],
                [
                    238,
                    312
                ],
                [
                    239,
                    311
                ],
                [
                    239,
                    309
                ],
                [
                    238,
                    308
                ],
                [
                    238,
                    306
                ],
                [
                    237,
                    305
                ],
                [
                    237,
                    304
                ],
                [
                    234,
                    301
                ],
                [
                    233,
                    301
                ],
                [
                    232,
                    300
                ]
            ]
        }
    ],
    "imagePath": "14414.png",
    "imageData": null,
    "imageHeight": 512,
    "imageWidth": 512
}