{
    "shapes": [
        {
            "label": "stroke",
            "points": [
                [
                    291,
                    217
                ],
                [
                    291,
                    219
                ],
                [
                    290,
                    220
                ],
                [
                    290,
                    222
                ],
                [
                    291,
                    223
                ],
                [
                    291,
                    224
                ],
                [
                    300,
                    233
                ],
                [
                    300,
                    234
                ],
                [
                    301,
                    235
                ],
                [
                    301,
                    240
                ],
                [
                    304,
                    240
                ],
                [
                    304,
                    239
                ],
                [
                    305,
                    238
                ],
                [
                    305,
                    229
                ],
                [
                    301,
                    225
                ],
                [
                    301,
                    220
                ],
                [
                    302,
                    219
                ],
                [
                    300,
                    217
                ]
            ]
        }
    ],
    "imagePath": "13340.png",
    "imageData": null,
    "imageHeight": 512,
    "imageWidth": 512
}