{
    "shapes": [
        {
            "label": "stroke",
            "points": [
                [
                    146,
                    267
                ],
                [
                    145,
                    268
                ],
                [
                    145,
                    278
                ],
                [
                    146,
                    279
                ],
                [
                    146,
                    280
                ],
                [
                    148,
                    282
                ],
                [
                    148,
                    283
                ],
                [
                    149,
                    284
                ],
                [
                    149,
                    286
                ],
                [
                    150,
                    287
                ],
                [
                    150,
                    289
                ],
                [
                    151,
                    290
                ],
                [
                    151,
                    294
                ],
                [
                    152,
                    295
                ],
                [
                    153,
                    295
                ],
                [
                    154,
                    296
                ],
                [
                    155,
                    296
                ],
                [
                    156,
                    297
                ],
                [
                    156,
                    298
                ],
                [
                    157,
                    299
                ],
                [
                    157,
                    301
                ],
                [
                    158,
                    302
                ],
                [
                    160,
                    302
                ],
                [
                    162,
                    304
                ],
                [
                    163,
                    304
                ],
                [
                    164,
                    305
                ],
                [
                    168,
                    305
                ],
                [
                    168,
                    304
                ],
                [
                    179,
                    293
                ],
                [
                    180,
                    293
                ],
                [
                    182,
                    291
                ],
                [
                    182,
                    290
                ],
                [
                    183,
                    289
                ],
                [
                    183,
                    287
                ],
                [
                    184,
                    286
                ],
                [
                    184,
                    285
                ],
                [
                    187,
                    282
                ],
                [
                    187,
                    281
                ],
                [
                    189,
                    279
                ],
                [
                    190,
                    279
                ],
                [
                    191,
                    278
                ],
                [
                    192,
                    278
                ],
                [
                    195,
                    275
                ],
                [
                    195,
                    274
                ],
                [
                    191,
                    274
                ],
                [
                    190,
                    273
                ],
                [
                    181,
                    273
                ],
                [
                    180,
                    272
                ],
                [
                    175,
                    272
                ],
                [
                    174,
                    271
                ],
                [
                    172,
                    271
                ],
                [
                    171,
                    270
                ],
                [
                    169,
                    270
                ],
                [
                    168,
                    269
                ],
                [
                    160,
                    269
                ],
                [
                    159,
                    268
                ],
                [
                    154,
                    268
                ],
                [
                    153,
                    267
                ]
            ]
        }
    ],
    "imagePath": "14931.png",
    "imageData": null,
    "imageHeight": 512,
    "imageWidth": 512
}