{
    "shapes": [
        {
            "label": "stroke",
            "points": [
                [
                    189,
                    225
                ],
                [
                    188,
                    226
                ],
                [
                    186,
                    226
                ],
                [
                    185,
                    227
                ],
                [
                    184,
                    227
                ],
                [
                    182,
                    229
                ],
                [
                    178,
                    229
                ],
                [
                    177,
                    230
                ],
                [
                    176,
                    230
                ],
                [
                    175,
                    231
                ],
                [
                    175,
                    240
                ],
                [
                    170,
                    245
                ],
                [
                    169,
                    245
                ],
                [
                    168,
                    246
                ],
                [
                    167,
                    246
                ],
                [
                    166,
                    245
                ],
                [
                    166,
                    241
                ],
                [
                    165,
                    240
                ],
                [
                    163,
                    240
                ],
                [
                    163,
                    248
                ],
                [
                    164,
                    249
                ],
                [
                    164,
                    250
                ],
                [
                    165,
                    251
                ],
                [
                    165,
                    255
                ],
                [
                    164,
                    256
                ],
                [
                    167,
                    256
                ],
                [
                    168,
                    255
                ],
                [
                    174,
                    255
                ],
                [
                    176,
                    253
                ],
                [
                    183,
                    253
                ],
                [
                    184,
                    252
                ],
                [
                    185,
                    252
                ],
                [
                    188,
                    249
                ],
                [
                    188,
                    248
                ],
                [
                    189,
                    247
                ],
                [
                    189,
                    239
                ],
                [
                    190,
                    238
                ],
                [
                    190,
                    237
                ],
                [
                    191,
                    236
                ],
                [
                    191,
                    235
                ],
                [
                    192,
                    234
                ],
                [
                    192,
                    230
                ],
                [
                    193,
                    229
                ],
                [
                    193,
                    228
                ],
                [
                    190,
                    225
                ]
            ]
        },
        {
            "label": "stroke",
            "points": [
                [
                    178,
                    193
                ],
                [
                    177,
                    194
                ],
                [
                    176,
                    194
                ],
                [
                    176,
                    195
                ],
                [
                    173,
                    198
                ],
                [
                    172,
                    197
                ],
                [
                    171,
                    198
                ],
                [
                    171,
                    201
                ],
                [
                    179,
                    201
                ],
                [
                    179,
                    200
                ],
                [
                    180,
                    199
                ],
                [
                    180,
                    195
                ],
                [
                    179,
                    194
                ],
                [
                    179,
                    193
                ]
            ]
        },
        {
            "label": "stroke",
            "points": [
                [
                    183,
                    144
                ],
                [
                    182,
                    145
                ],
                [
                    181,
                    145
                ],
                [
                    180,
                    146
                ],
                [
                    180,
                    154
                ],
                [
                    179,
                    155
                ],
                [
                    178,
                    155
                ],
                [
                    178,
                    160
                ],
                [
                    177,
                    161
                ],
                [
                    177,
                    177
                ],
                [
                    178,
                    178
                ],
                [
                    178,
                    179
                ],
                [
                    179,
                    179
                ],
                [
                    180,
                    180
                ],
                [
                    183,
                    180
                ],
                [
                    184,
                    179
                ],
                [
                    187,
                    179
                ],
                [
                    188,
                    178
                ],
                [
                    189,
                    178
                ],
                [
                    190,
                    177
                ],
                [
                    191,
                    177
                ],
                [
                    191,
                    176
                ],
                [
                    192,
                    175
                ],
                [
                    192,
                    172
                ],
                [
                    191,
                    171
                ],
                [
                    191,
                    167
                ],
                [
                    190,
                    166
                ],
                [
                    190,
                    162
                ],
                [
                    193,
                    159
                ],
                [
                    193,
                    147
                ],
                [
                    192,
                    146
                ],
                [
                    191,
                    146
                ],
                [
                    190,
                    145
                ],
                [
                    186,
                    145
                ],
                [
                    185,
                    144
                ]
            ]
        }
    ],
    "imagePath": "16496.png",
    "imageData": null,
    "imageHeight": 512,
    "imageWidth": 512
}